{
  "uid": "chg_mqkv3xev_d4915350-b0e4-4d07-9849-1066ce59a2cd",
  "id": 1781869525779734,
  "category": "handler",
  "key": "getWeather",
  "action": "create",
  "beforeSnapshot": null,
  "afterSnapshot": {
    "name": "getWeather",
    "source": "\n// Fetch weather data for a lat/lon position — returns nautical/metric units\nasync function getWeather(c) {\n  const lat = parseFloat(c.req.query('lat'));\n  const lon = parseFloat(c.req.query('lon'));\n\n  // Validate coordinates\n  if (isNaN(lat) || isNaN(lon)) {\n    return c.json({ error: true, message: 'lat and lon query parameters are required' }, 400);\n  }\n  if (lat < -90 || lat > 90 || lon < -180 || lon > 180) {\n    return c.json({ error: true, message: 'Invalid coordinates: lat must be -90..90, lon must be -180..180' }, 400);\n  }\n\n  try {\n    const weather = await functions.call('fetchWeather', lat, lon);\n    return c.json(weather);\n  } catch (err) {\n    log.error('Weather fetch failed: ' + err.message);\n    return c.json({ error: true, message: 'Failed to fetch weather data' }, 500);\n  }\n}\n",
    "schema": {
      "query": {
        "lat": {
          "description": "Latitude (-90 to 90)",
          "required": true,
          "type": "number"
        },
        "lon": {
          "description": "Longitude (-180 to 180)",
          "required": true,
          "type": "number"
        }
      },
      "responses": {
        "200": {
          "description": "Weather data with current conditions and hourly forecast",
          "schema": {
            "properties": {
              "current": {
                "type": "object"
              },
              "hourly": {
                "type": "array"
              },
              "latitude": {
                "type": "number"
              },
              "longitude": {
                "type": "number"
              }
            },
            "type": "object"
          }
        },
        "400": {
          "description": "Missing or invalid coordinates"
        },
        "500": {
          "description": "Weather API error"
        }
      },
      "summary": "Get weather data for a position",
      "tags": [
        "weather"
      ]
    },
    "module": "weather",
    "runtimeId": "typescript",
    "language": "typescript"
  },
  "context": {
    "userMessage": "Approved. Go ahead with the plan.",
    "turnId": "turn_mqkv1oz5_cc1839de-2ce2-4f4a-89f1-54697456a1f3",
    "turnIndex": 1,
    "sessionId": "session_mqkpyhwq_25b64e78-6973-4cf9-adce-df24408b5c74",
    "changesetId": "cs_mqkqjkbc_f0e212e6-4bda-4ec8-a1a3-0dda7f345bcf",
    "toolCallId": "sevt_012D4nWUpCWnvsF41BBdDjNX"
  },
  "createdAt": "2026-06-19T11:45:25.735Z",
  "undoable": true,
  "turnId": "turn_mqkv1oz5_cc1839de-2ce2-4f4a-89f1-54697456a1f3",
  "changesetId": "cs_mqkqjkbc_f0e212e6-4bda-4ec8-a1a3-0dda7f345bcf",
  "rationale": "API endpoint for fetching weather data at a given position. Used by the client-side map to display conditions.",
  "implementation": "Extracts lat/lon from query params, validates them, then delegates to fetchWeather function. Returns JSON with current + hourly forecast data in nautical/metric units.",
  "workMessageId": 1781869525773835
}
